netaddr_pydantic/__init__.py
netaddr_pydantic/friends.py
netaddr_pydantic/py.typed
netaddr_pydantic-0.2.1.dist-info/LICENSE
netaddr_pydantic-0.2.1.dist-info/METADATA
netaddr_pydantic-0.2.1.dist-info/WHEEL
netaddr_pydantic-0.2.1.dist-info/RECORD
