Metadata-Version: 2.3
Name: netaddr-pydantic
Version: 0.2.1
Summary: Use Netaddr objects in Pydantic Models
License: LGPL-2.1-or-later
Keywords: pydantic,netaddr
Author: Damien Nadé
Author-email: anvil.github+netaddr-pydantic@livna.org
Requires-Python: >=3.11
Classifier: Framework :: Pydantic :: 2
Classifier: Intended Audience :: Developers
Classifier: Programming Language :: Python
Classifier: Programming Language :: Python :: 3 :: Only
Classifier: Programming Language :: Python :: 3
Classifier: Programming Language :: Python :: 3.13
Classifier: Programming Language :: Python :: 3.12
Classifier: Programming Language :: Python :: 3.11
Classifier: Topic :: Software Development
Classifier: Typing :: Typed
Requires-Dist: netaddr (>=1.3.0)
Requires-Dist: pydantic (>=2.11)
Requires-Dist: pydantic-core (>=2.33)
Requires-Dist: types-netaddr (>=1.3.0)
Project-URL: Documentation, https://github.com/Anvil/netaddr-pydantic/README.md
Project-URL: Issues, https://github.com/Anvil/netaddr-pydantic/issues
Project-URL: Repository, https://github.com/Anvil/netaddr-pydantic/
